dragonfly_schema/__init__.py
dragonfly_schema/model.py
dragonfly_schema/roof.py
dragonfly_schema/shading_parameter.py
dragonfly_schema/skylight_parameter.py
dragonfly_schema/window_parameter.py
dragonfly_schema/comparison/__init__.py
dragonfly_schema/comparison/properties.py
dragonfly_schema/doe2/__init__.py
dragonfly_schema/doe2/properties.py
dragonfly_schema/energy/__init__.py
dragonfly_schema/energy/properties.py
dragonfly_schema/radiance/__init__.py
dragonfly_schema/radiance/gridpar.py
dragonfly_schema/radiance/properties.py
dragonfly_schema-1.15.3.dist-info/licenses/LICENSE
dragonfly_schema-1.15.3.dist-info/METADATA
dragonfly_schema-1.15.3.dist-info/WHEEL
dragonfly_schema-1.15.3.dist-info/top_level.txt
dragonfly_schema-1.15.3.dist-info/RECORD
