Metadata-Version: 2.4
Name: dragonfly-schema
Version: 1.15.3
Summary: Dragonfly Data-Model Objects
Home-page: https://github.com/ladybug-tools/dragonfly-schema
Author: Ladybug Tools
Author-email: info@ladybug.tools
License: MIT
Classifier: Programming Language :: Python :: 3.7
Classifier: Programming Language :: Python :: 3.8
Classifier: Programming Language :: Python :: 3.9
Classifier: Programming Language :: Python :: 3.10
Classifier: Programming Language :: Python :: 3.11
Classifier: Programming Language :: Python :: 3.12
Classifier: Programming Language :: Python :: Implementation :: CPython
Classifier: Operating System :: OS Independent
License-File: LICENSE
Requires-Dist: honeybee-schema==1.59.1
Dynamic: author
Dynamic: author-email
Dynamic: classifier
Dynamic: description
Dynamic: description-content-type
Dynamic: home-page
Dynamic: license
Dynamic: license-file
Dynamic: requires-dist
Dynamic: summary
